annodize/__init__.py
annodize/_field.py
annodize/_func_fields.py
annodize/_nsp_fields.py
annodize/_plugins.py
annodize/_repr.py
annodize/field.py
annodize/py.typed
annodize/version.py
annodize/frame/__init__.py
annodize/frame/_load.py
annodize/frame/_schema.py
annodize/frame/_typeddict.py
annodize/test/__init__.py
annodize/test/test_field.py
annodize/test/test_func_fields.py
annodize/test/test_minimal.py
annodize/test/test_nsp_fields.py
annodize-0.2.0.dist-info/LICENSE
annodize-0.2.0.dist-info/METADATA
annodize-0.2.0.dist-info/WHEEL
annodize-0.2.0.dist-info/entry_points.txt
annodize-0.2.0.dist-info/top_level.txt
annodize-0.2.0.dist-info/RECORD
